selenium2df_locate_element/README.MD
selenium2df_locate_element/__init__.py
selenium2df_locate_element/requirements.txt
selenium2df_locate_element/thirdparty.json
selenium2df_locate_element-0.10.dist-info/LICENSE.rst
selenium2df_locate_element-0.10.dist-info/METADATA
selenium2df_locate_element-0.10.dist-info/WHEEL
selenium2df_locate_element-0.10.dist-info/top_level.txt
selenium2df_locate_element-0.10.dist-info/RECORD
