Metadata-Version: 2.1
Name: selenium2df-locate-element
Version: 0.10
Summary: Like WebDriverWait - visibility_of_element_located, but much easier
Home-page: https://github.com/hansalemaos/selenium2df_locate_element
Author: Johannes Fischer
Author-email: aulasparticularesdealemaosp@gmail.com
License: MIT
Keywords: selenium,WebDriverWait,visibility_of_element_located
Classifier: Development Status :: 4 - Beta
Classifier: Programming Language :: Python :: 3 :: Only
Classifier: Programming Language :: Python :: 3.10
Classifier: Topic :: Software Development :: Libraries :: Python Modules
Classifier: Topic :: Utilities
License-File: LICENSE.rst
Requires-Dist: a-selenium2df
Requires-Dist: pandas
Requires-Dist: selenium
